asx_terminus-0.1.6.dist-info/DESCRIPTION.rst
asx_terminus-0.1.6.dist-info/METADATA
asx_terminus-0.1.6.dist-info/RECORD
asx_terminus-0.1.6.dist-info/WHEEL
asx_terminus-0.1.6.dist-info/entry_points.txt
asx_terminus-0.1.6.dist-info/metadata.json
asx_terminus-0.1.6.dist-info/top_level.txt
asxterminus/__init__.py
asxterminus/cli.py
asxterminus/config.py
asxterminus/data/__init__.py
asxterminus/data/base.py
asxterminus/data/news.py
asxterminus/data/rss.py
asxterminus/data/share.py
asxterminus/tests/__init__.py
asxterminus/tests/data/__init__.py
asxterminus/tests/data/test_share.py
asxterminus/tests/ui/__init__.py
asxterminus/tests/ui/test_portfolio.py
asxterminus/tests/ui/test_row.py
asxterminus/tests/ui/test_table.py
asxterminus/ui/__init__.py
asxterminus/ui/app.py
asxterminus/ui/news.py
asxterminus/ui/portfolio.py
asxterminus/ui/table.py
