Metadata-Version: 2.0
Name: asx-terminus
Version: 0.1.6
Summary: ASX portfolio in the terminal
Home-page: UNKNOWN
Author: Nam Ngo
Author-email: namngology@gmail.com
License: Apache 2.0
Keywords: asx,terminal,urwid,ncurses,australia,investment,stock
Platform: UNKNOWN
Requires-Dist: requests (>=2.18.4)
Requires-Dist: urwid (>=1.3.1)
Requires-Dist: urwid-timed-progress (==1.1.1)
Requires-Dist: pyyaml (>=3.12)
Requires-Dist: beautifulsoup4 (==4.6.0)
Requires-Dist: feedparser (==5.2.1)
